previsedx_quantstudio_file_utils/__init__.py
previsedx_quantstudio_file_utils/console_helper.py
previsedx_quantstudio_file_utils/constants.py
previsedx_quantstudio_file_utils/file_utils.py
previsedx_quantstudio_file_utils/parser.py
previsedx_quantstudio_file_utils/record.py
previsedx_quantstudio_file_utils/system_caller.py
previsedx_quantstudio_file_utils/conf/config.yaml
previsedx_quantstudio_file_utils/xls/__init__.py
previsedx_quantstudio_file_utils/xls/parser.py
previsedx_quantstudio_file_utils-0.1.0.dist-info/AUTHORS.rst
previsedx_quantstudio_file_utils-0.1.0.dist-info/LICENSE
previsedx_quantstudio_file_utils-0.1.0.dist-info/METADATA
previsedx_quantstudio_file_utils-0.1.0.dist-info/WHEEL
previsedx_quantstudio_file_utils-0.1.0.dist-info/top_level.txt
previsedx_quantstudio_file_utils-0.1.0.dist-info/RECORD
