Metadata-Version: 2.1
Name: previsedx_quantstudio_file_utils
Version: 0.1.0
Summary: Collection of modules for processing QuantStudio files.
Home-page: https://github.com/sundaram-previsedx/previsedx-quantstudio-file-utils
Author: Jaideep Sundaram
Author-email: sundaram.previse@gmail.com
Keywords: previsedx_quantstudio_file_utils
Classifier: Development Status :: 2 - Pre-Alpha
Classifier: Intended Audience :: Developers
Classifier: Natural Language :: English
Classifier: Programming Language :: Python :: 3
Classifier: Programming Language :: Python :: 3.6
Classifier: Programming Language :: Python :: 3.7
Classifier: Programming Language :: Python :: 3.8
Requires-Python: >=3.6
License-File: LICENSE
License-File: AUTHORS.rst
Requires-Dist: Click>=7.0
Requires-Dist: Rich
Requires-Dist: PyYAML
Requires-Dist: Pydantic
Requires-Dist: pandas
Requires-Dist: xlrd==2.0.1
